{
  "data_science_tech": [
    {
      "video_id": "N3o-0dTZ2r8",
      "title": "Al Sweigart's Python Tutorial at PyCon US 2026",
      "channel": "Al Sweigart",
      "url": "https://youtu.be/N3o-0dTZ2r8",
      "published_at": "2026-04-29T18:21:48Z",
      "views": 198,
      "likes": 25,
      "comments": 1,
      "engagement_rate": 0.13131313131313133
    },
    {
      "video_id": "3FIjuvnPxaI",
      "title": "AI on the Edge LESSON 10: Make Your Raspberry Pi Listen to You with Voice Commands",
      "channel": "Paul McWhorter",
      "url": "https://youtu.be/3FIjuvnPxaI",
      "published_at": "2026-04-29T16:00:06Z",
      "views": 619,
      "likes": 78,
      "comments": 0,
      "engagement_rate": 0.1260096930533118
    },
    {
      "video_id": "Fmwx-4U-WYM",
      "title": "\ud83d\udc49 Build Your First Web App using Streamlit (Python Tutorial)",
      "channel": "UiPath RPA",
      "url": "https://youtu.be/Fmwx-4U-WYM",
      "published_at": "2026-04-29T12:13:29Z",
      "views": 30,
      "likes": 2,
      "comments": 1,
      "engagement_rate": 0.1
    },
    {
      "video_id": "EoV65TNHCaI",
      "title": "Python Zero to Hero with AI | Complete Beginner to Advanced Guide \ud83d\ude80",
      "channel": "Accounts Expert",
      "url": "https://youtu.be/EoV65TNHCaI",
      "published_at": "2026-04-27T14:06:22Z",
      "views": 3677,
      "likes": 312,
      "comments": 43,
      "engagement_rate": 0.09654609736197987
    },
    {
      "video_id": "EoV65TNHCaI",
      "title": "Python Zero to Hero with AI | Complete Beginner to Advanced Guide \ud83d\ude80",
      "channel": "Accounts Expert",
      "url": "https://youtu.be/EoV65TNHCaI",
      "published_at": "2026-04-27T14:06:22Z",
      "views": 3677,
      "likes": 312,
      "comments": 43,
      "engagement_rate": 0.09654609736197987
    },
    {
      "video_id": "xs3YM5GoGcQ",
      "title": "Complete Maths for Machine Learning &  Data Science - FREE Full Course (2026)",
      "channel": "Coding With Sagar",
      "url": "https://youtu.be/xs3YM5GoGcQ",
      "published_at": "2026-04-24T09:54:23Z",
      "views": 18207,
      "likes": 1116,
      "comments": 191,
      "engagement_rate": 0.07178557697588839
    },
    {
      "video_id": "dsTFg25sptM",
      "title": "Build an AI Agent From Scratch in Python - Tutorial for Beginners",
      "channel": "Sagar.Utekar",
      "url": "https://youtu.be/dsTFg25sptM",
      "published_at": "2026-04-28T13:30:06Z",
      "views": 678,
      "likes": 39,
      "comments": 9,
      "engagement_rate": 0.07079646017699115
    },
    {
      "video_id": "rVVx8CfT4tk",
      "title": "University of Alabama proposes first school of data science",
      "channel": "WVTM 13 News",
      "url": "https://youtu.be/rVVx8CfT4tk",
      "published_at": "2026-04-28T23:55:50Z",
      "views": 103,
      "likes": 6,
      "comments": 1,
      "engagement_rate": 0.06796116504854369
    },
    {
      "video_id": "ehBsSKEh3UU",
      "title": "AI, Machine Learning and Student Projects \u2013 Where to Start? | Data Science Club",
      "channel": "PJATK",
      "url": "https://youtu.be/ehBsSKEh3UU",
      "published_at": "2026-04-28T09:00:54Z",
      "views": 108,
      "likes": 6,
      "comments": 1,
      "engagement_rate": 0.06481481481481481
    },
    {
      "video_id": "we1Xh28vZjs",
      "title": "I Hired Data Scientists at Big Tech - This is Why You Get Rejected",
      "channel": "Andrey Yasinsky",
      "url": "https://youtu.be/we1Xh28vZjs",
      "published_at": "2026-04-23T20:29:31Z",
      "views": 441,
      "likes": 19,
      "comments": 4,
      "engagement_rate": 0.05215419501133787
    }
  ],
  "life_self_dev": [
    {
      "video_id": "xG0jn-9_OF8",
      "title": "Habits I'm Building This Year & Why  | Real Life, No Hustle Culture",
      "channel": "Somya Nayak",
      "url": "https://youtu.be/xG0jn-9_OF8",
      "published_at": "2026-04-29T12:15:15Z",
      "views": 36,
      "likes": 5,
      "comments": 5,
      "engagement_rate": 0.2777777777777778
    },
    {
      "video_id": "iFPASaSdR6w",
      "title": "How to Build a Habit Tracker App With No Code in 2026 (Base44 Tutorial)",
      "channel": "George Vlasyev",
      "url": "https://youtu.be/iFPASaSdR6w",
      "published_at": "2026-04-29T15:48:39Z",
      "views": 7,
      "likes": 0,
      "comments": 1,
      "engagement_rate": 0.14285714285714285
    },
    {
      "video_id": "KKp7oh1IHXU",
      "title": "self destruction is better that self improvement",
      "channel": "Andy's Story",
      "url": "https://youtu.be/KKp7oh1IHXU",
      "published_at": "2026-04-25T08:58:18Z",
      "views": 8455,
      "likes": 780,
      "comments": 125,
      "engagement_rate": 0.10703725606150206
    },
    {
      "video_id": "L94Q1iRXzhw",
      "title": "\ud83c\udf31 Learning a New Habit Is That Easy? | Build Better Habits for Success",
      "channel": "The Mindset Shift",
      "url": "https://youtu.be/L94Q1iRXzhw",
      "published_at": "2026-04-25T15:21:50Z",
      "views": 29,
      "likes": 3,
      "comments": 0,
      "engagement_rate": 0.10344827586206896
    },
    {
      "video_id": "UzpbXmUpHxA",
      "title": "5 Simple Suggestions to Double Your Productivity Today",
      "channel": "Carl Pullein",
      "url": "https://youtu.be/UzpbXmUpHxA",
      "published_at": "2026-04-29T23:15:01Z",
      "views": 227,
      "likes": 19,
      "comments": 1,
      "engagement_rate": 0.0881057268722467
    },
    {
      "video_id": "0uw_dNuQWts",
      "title": "Staying sober when life is challenging takes character #motivation #selfimprovement #discipline",
      "channel": "Rizzy BDG",
      "url": "https://youtu.be/0uw_dNuQWts",
      "published_at": "2026-04-25T18:09:28Z",
      "views": 17718,
      "likes": 998,
      "comments": 52,
      "engagement_rate": 0.05926176769387064
    },
    {
      "video_id": "eCHeQ23aaWE",
      "title": "The Hardest Part of Self-Improvement",
      "channel": "Mark Manson",
      "url": "https://youtu.be/eCHeQ23aaWE",
      "published_at": "2026-04-27T13:01:57Z",
      "views": 35688,
      "likes": 1930,
      "comments": 49,
      "engagement_rate": 0.055452813270567135
    },
    {
      "video_id": "VF07FCbNpD8",
      "title": "15 Wealth Building Habits That Quietly Make People Rich",
      "channel": "Alux.com",
      "url": "https://youtu.be/VF07FCbNpD8",
      "published_at": "2026-04-26T17:32:33Z",
      "views": 36461,
      "likes": 1782,
      "comments": 164,
      "engagement_rate": 0.05337209621239132
    },
    {
      "video_id": "UJtc8iSKfdI",
      "title": "How To Be Productivity#study #students #shorts#exam",
      "channel": "Easy to find ",
      "url": "https://youtu.be/UJtc8iSKfdI",
      "published_at": "2026-04-25T23:44:30Z",
      "views": 11698,
      "likes": 584,
      "comments": 6,
      "engagement_rate": 0.050435971961018976
    },
    {
      "video_id": "W41Je11IPXA",
      "title": "Warren Buffett: 5 Small Habits That Secretly Build Fortunes (Most People Ignore #3)",
      "channel": "The Legend Investor",
      "url": "https://youtu.be/W41Je11IPXA",
      "published_at": "2026-04-23T16:07:04Z",
      "views": 1197,
      "likes": 46,
      "comments": 3,
      "engagement_rate": 0.04093567251461988
    }
  ],
  "poetry_quotes": [
    {
      "video_id": "s2tDUHhOkaI",
      "title": "This creative writing exercise is \ud83d\udd25#authors #writingprompts",
      "channel": "A Space to Write",
      "url": "https://youtu.be/s2tDUHhOkaI",
      "published_at": "2026-04-27T14:47:07Z",
      "views": 13734,
      "likes": 2603,
      "comments": 27,
      "engagement_rate": 0.19149555846803554
    },
    {
      "video_id": "0wYLe4WZMbk",
      "title": "How a Nobel Prize Winner Writes Dystopia",
      "channel": "Creative Writing Corner",
      "url": "https://youtu.be/0wYLe4WZMbk",
      "published_at": "2026-04-28T17:00:06Z",
      "views": 69,
      "likes": 9,
      "comments": 4,
      "engagement_rate": 0.18840579710144928
    },
    {
      "video_id": "GzfWOLGYkDg",
      "title": "My best selling poetry books including my new book AJAR and my debute novel are available on Amazon!",
      "channel": "Kori Jane Spaulding",
      "url": "https://youtu.be/GzfWOLGYkDg",
      "published_at": "2026-04-29T20:46:56Z",
      "views": 2396,
      "likes": 323,
      "comments": 2,
      "engagement_rate": 0.13564273789649417
    },
    {
      "video_id": "WjF-3RRGjxI",
      "title": "Discover it in the M.A. in English (Creative Writing) program at Alliance University",
      "channel": "Alliance University",
      "url": "https://youtu.be/WjF-3RRGjxI",
      "published_at": "2026-04-27T12:22:18Z",
      "views": 84,
      "likes": 10,
      "comments": 0,
      "engagement_rate": 0.11904761904761904
    },
    {
      "video_id": "I4MfF7vbuks",
      "title": "AskAbbie LIVE: Writing & Creativity Q&A (Plus Live Chat Questions!)",
      "channel": "Abbie Emmons",
      "url": "https://youtu.be/I4MfF7vbuks",
      "published_at": "2026-04-29T16:43:39Z",
      "views": 1940,
      "likes": 215,
      "comments": 6,
      "engagement_rate": 0.11391752577319587
    },
    {
      "video_id": "KnF7k1FPWsE",
      "title": "Writes of Spring 2026 Poetry Readings",
      "channel": "McNally Robinson Online Events",
      "url": "https://youtu.be/KnF7k1FPWsE",
      "published_at": "2026-04-27T08:18:35Z",
      "views": 62,
      "likes": 7,
      "comments": 0,
      "engagement_rate": 0.11290322580645161
    },
    {
      "video_id": "ANwOGlKm8Yk",
      "title": "Creative Writing & Meditation with Peter Jaeger",
      "channel": "meditatiowccm",
      "url": "https://youtu.be/ANwOGlKm8Yk",
      "published_at": "2026-04-27T10:44:20Z",
      "views": 79,
      "likes": 4,
      "comments": 4,
      "engagement_rate": 0.10126582278481013
    },
    {
      "video_id": "BqWOMjxVRvk",
      "title": "If a woman leaves you for another man. #motivation #ytshorts #motivational #quotes #inspiration #yt",
      "channel": "Daily Motivation Podcast",
      "url": "https://youtu.be/BqWOMjxVRvk",
      "published_at": "2026-04-27T02:14:49Z",
      "views": 21755,
      "likes": 1601,
      "comments": 42,
      "engagement_rate": 0.07552286830613653
    },
    {
      "video_id": "_g0naoaC6lc",
      "title": "Mountain Talk: A Poetry Reading from Wendell Berry, from the Appalshop Archive; Plus, Trad. Crafting",
      "channel": "Appalshop",
      "url": "https://youtu.be/_g0naoaC6lc",
      "published_at": "2026-04-25T12:30:50Z",
      "views": 61,
      "likes": 4,
      "comments": 0,
      "engagement_rate": 0.06557377049180328
    },
    {
      "video_id": "en8aC-rkae4",
      "title": "My voice is \u201c Sleepy \u201c \ud83d\ude30#fun#art#writing#creative#song#trending#english#shorts",
      "channel": "@Rehnumaartgallery",
      "url": "https://youtu.be/en8aC-rkae4",
      "published_at": "2026-04-29T05:26:18Z",
      "views": 19458,
      "likes": 658,
      "comments": 299,
      "engagement_rate": 0.04918285538082023
    }
  ]
}